de2_sentiment_analyzer/__init__.py
de2_sentiment_analyzer/app.py
de2_sentiment_analyzer-1.0.1.dist-info/METADATA
de2_sentiment_analyzer-1.0.1.dist-info/WHEEL
de2_sentiment_analyzer-1.0.1.dist-info/top_level.txt
de2_sentiment_analyzer-1.0.1.dist-info/RECORD
