Metadata-Version: 2.1
Name: de2-sentiment-analyzer
Version: 1.0.1
Summary: Sentiment analyzer app
Author-email: prabhu <prabhupad@somwwhe.com>
Classifier: Programming Language :: Python :: 3
Classifier: License :: OSI Approved :: MIT License
Classifier: Operating System :: OS Independent
Requires-Python: >=3.7
